casual_inference/__init__.py
casual_inference/dataset/__init__.py
casual_inference/dataset/sample_abtest.py
casual_inference/dataset/sample_biased.py
casual_inference/evaluator/__init__.py
casual_inference/evaluator/aatest.py
casual_inference/evaluator/abtest.py
casual_inference/evaluator/base.py
casual_inference/evaluator/linear_regression.py
casual_inference/evaluator/samplesize.py
casual_inference/statistical_testing.py
casual_inference-0.7.1.dist-info/LICENSE
casual_inference-0.7.1.dist-info/METADATA
casual_inference-0.7.1.dist-info/WHEEL
casual_inference-0.7.1.dist-info/RECORD
