Metadata-Version: 2.1
Name: casual_inference
Version: 0.7.1
Summary: Do causal inference more casually
Home-page: https://github.com/shyaginuma
License: MIT
Author: yaginuuun
Author-email: yaginuuun@gmail.com
Requires-Python: >=3.10,<3.12
Classifier: License :: OSI Approved :: MIT License
Classifier: Programming Language :: Python :: 3
Classifier: Programming Language :: Python :: 3.10
Classifier: Programming Language :: Python :: 3.11
Requires-Dist: lxml (>=4.9.1,<5.0.0)
Requires-Dist: numpy (==1.26.4)
Requires-Dist: pandas (>=1.4.3,<2.0.0)
Requires-Dist: plotly (>=5.10.0,<6.0.0)
Requires-Dist: scikit-learn (>=1.1.3,<2.0.0)
Requires-Dist: scipy (>=1.14.1,<2.0.0)
Requires-Dist: statsmodels (>=0.13.5,<0.14.0)
Requires-Dist: typing-extensions (>=4.3.0,<5.0.0)
Project-URL: Repository, https://github.com/shyaginuma/casual_inference
